{
  "time": "2026-06-09T11:45:56+00:00",
  "list": [
    {
      "name": "skyward_harp",
      "type": "weapon",
      "count": 3036,
      "guaranteed": 1
    },
    {
      "name": "favonius_sword",
      "type": "weapon",
      "count": 180325,
      "guaranteed": 42150
    },
    {
      "name": "sacrificial_greatsword",
      "type": "weapon",
      "count": 180871,
      "guaranteed": 42061
    },
    {
      "name": "wolfs_gravestone",
      "type": "weapon",
      "count": 3052,
      "guaranteed": 2
    },
    {
      "name": "aquila_favonia",
      "type": "weapon",
      "count": 3081,
      "guaranteed": 3
    },
    {
      "name": "favonius_codex",
      "type": "weapon",
      "count": 180882,
      "guaranteed": 42344
    },
    {
      "name": "favonius_lance",
      "type": "weapon",
      "count": 179387,
      "guaranteed": 42131
    },
    {
      "name": "skyward_spine",
      "type": "weapon",
      "count": 49767,
      "guaranteed": 8070
    },
    {
      "name": "primordial_jade_winged-spear",
      "type": "weapon",
      "count": 3154,
      "guaranteed": 2
    },
    {
      "name": "amos_bow",
      "type": "weapon",
      "count": 3074,
      "guaranteed": 2
    },
    {
      "name": "skyward_atlas",
      "type": "weapon",
      "count": 2993,
      "guaranteed": 0
    },
    {
      "name": "skyward_blade",
      "type": "weapon",
      "count": 2964,
      "guaranteed": 0
    },
    {
      "name": "mistsplitter_reforged",
      "type": "weapon",
      "count": 62700,
      "guaranteed": 11189
    },
    {
      "name": "the_stringless",
      "type": "weapon",
      "count": 180041,
      "guaranteed": 41996
    },
    {
      "name": "lost_prayer_to_the_sacred_winds",
      "type": "weapon",
      "count": 3063,
      "guaranteed": 0
    }
  ],
  "pityAverage": {
    "legendary": 49.50445632798574,
    "rare": 6.6470856380120855
  },
  "median": {
    "legendary": 63
  },
  "pityCount": {
    "legendary": [
      0,
      1206,
      1280,
      1267,
      1276,
      1327,
      1239,
      1257,
      1221,
      1147,
      1155,
      1097,
      1132,
      1097,
      1114,
      1092,
      1081,
      981,
      1020,
      1053,
      1014,
      1013,
      980,
      987,
      932,
      955,
      976,
      963,
      918,
      1036,
      946,
      969,
      915,
      885,
      925,
      947,
      919,
      932,
      914,
      891,
      863,
      903,
      867,
      942,
      888,
      974,
      961,
      904,
      974,
      941,
      957,
      920,
      967,
      1063,
      1076,
      1170,
      1236,
      1123,
      1195,
      1177,
      1095,
      1168,
      1281,
      6111,
      10091,
      12545,
      12608,
      11241,
      8495,
      5614,
      3074,
      1469,
      592,
      209,
      51,
      16,
      8,
      3,
      5,
      8,
      7,
      5,
      4,
      2,
      3,
      2,
      4,
      2,
      4,
      6,
      1,
      0,
      0,
      0,
      0,
      0,
      0,
      0,
      0,
      0,
      0
    ],
    "rare": [
      71212,
      66845,
      63397,
      59109,
      55094,
      52076,
      49550,
      471692,
      238103,
      2689
    ]
  },
  "total": {
    "legendary": 136884,
    "rare": 901506,
    "all": 7732159,
    "users": 268504
  },
  "countEachPity": [
    124581,
    120672,
    116418,
    112478,
    108724,
    105021,
    101552,
    98355,
    95485,
    92955,
    93096,
    92467,
    91887,
    91182,
    90635,
    90052,
    89472,
    89027,
    88583,
    87967,
    88168,
    87858,
    87447,
    87013,
    86649,
    86369,
    86011,
    85647,
    85385,
    84849,
    85052,
    84741,
    84505,
    84295,
    83959,
    83657,
    83285,
    82941,
    82603,
    82250,
    82461,
    82249,
    81970,
    81639,
    81268,
    80856,
    80385,
    79979,
    79496,
    79027,
    79015,
    78676,
    78208,
    77630,
    77031,
    76346,
    75543,
    74836,
    74067,
    73272,
    72820,
    72022,
    71128,
    65362,
    55545,
    43180,
    30683,
    19497,
    11045,
    5459,
    2390,
    924,
    334,
    126,
    77,
    61,
    54,
    51,
    46,
    38,
    31,
    26,
    23,
    21,
    18,
    16,
    12,
    10,
    6,
    1
  ],
  "pullByDay": [
    {
      "day": "2021-07-21T22:00:00.000Z",
      "percentage": 0.10795922103701135
    },
    {
      "day": "2021-07-22T22:00:00.000Z",
      "percentage": 0.08801226645082338
    },
    {
      "day": "2021-07-23T22:00:00.000Z",
      "percentage": 0.07538615712234653
    },
    {
      "day": "2021-07-24T22:00:00.000Z",
      "percentage": 0.0577050752078937
    },
    {
      "day": "2021-07-25T22:00:00.000Z",
      "percentage": 0.051281569489010304
    },
    {
      "day": "2021-07-26T22:00:00.000Z",
      "percentage": 0.05241281954923443
    },
    {
      "day": "2021-07-27T22:00:00.000Z",
      "percentage": 0.04089941124890392
    },
    {
      "day": "2021-07-28T22:00:00.000Z",
      "percentage": 0.03821895566540437
    },
    {
      "day": "2021-07-29T22:00:00.000Z",
      "percentage": 0.040983725031075655
    },
    {
      "day": "2021-07-30T22:00:00.000Z",
      "percentage": 0.04135326029350832
    },
    {
      "day": "2021-07-31T22:00:00.000Z",
      "percentage": 0.0886383565075786
    },
    {
      "day": "2021-08-01T22:00:00.000Z",
      "percentage": 0.04541188487073493
    },
    {
      "day": "2021-08-02T22:00:00.000Z",
      "percentage": 0.03734618757166672
    },
    {
      "day": "2021-08-03T22:00:00.000Z",
      "percentage": 0.034288969830119774
    },
    {
      "day": "2021-08-04T22:00:00.000Z",
      "percentage": 0.034347507684599
    },
    {
      "day": "2021-08-05T22:00:00.000Z",
      "percentage": 0.03652473043679357
    },
    {
      "day": "2021-08-06T22:00:00.000Z",
      "percentage": 0.038842877653475175
    },
    {
      "day": "2021-08-07T22:00:00.000Z",
      "percentage": 0.03443567581109858
    },
    {
      "day": "2021-08-08T22:00:00.000Z",
      "percentage": 0.033164705768989874
    },
    {
      "day": "2021-08-09T22:00:00.000Z",
      "percentage": 0.022332793725127434
    },
    {
      "day": "2021-08-10T22:00:00.000Z",
      "percentage": 0.00045384904460439975
    }
  ],
  "constellation": {
    "amos_bow": [
      3055,
      16,
      3
    ],
    "aquila_favonia": [
      3061,
      20
    ],
    "favonius_codex": [
      58166,
      44174,
      28257,
      17516,
      12065,
      7092,
      4158,
      9454
    ],
    "favonius_lance": [
      58225,
      42768,
      28797,
      18112,
      11370,
      6432,
      4242,
      9441
    ],
    "favonius_sword": [
      57808,
      43364,
      29151,
      18236,
      11365,
      7188,
      4095,
      9118
    ],
    "lost_prayer_to_the_sacred_winds": [
      3051,
      12
    ],
    "mistsplitter_reforged": [
      57109,
      2816,
      453,
      168,
      1685,
      318,
      35,
      116
    ],
    "primordial_jade_winged-spear": [
      3140,
      14
    ],
    "sacrificial_greatsword": [
      58336,
      43182,
      28818,
      18060,
      12035,
      6924,
      4116,
      9400
    ],
    "skyward_atlas": [
      2979,
      14
    ],
    "skyward_blade": [
      2934,
      30
    ],
    "skyward_harp": [
      3006,
      30
    ],
    "skyward_spine": [
      35688,
      12062,
      1014,
      388,
      295,
      138,
      112,
      70
    ],
    "the_stringless": [
      58682,
      43484,
      28632,
      18176,
      11245,
      7176,
      3997,
      8649
    ],
    "wolfs_gravestone": [
      3022,
      30
    ]
  }
}